{
    "shopName": "Gæy Sombr Shop",
    "shopSubtitle": "Premium Roblox Items & Services",
    "shopDescription": "We provide high-quality Roblox items and accessories to enhance your gaming experience. All items are officially licensed.",
    "popupTitle": "Welcome to Gæy Sombr Shop!",
    "popupMessage": "Thank you for visiting our Roblox item shop. We offer exclusive, high-quality items to enhance your Roblox experience. Click the 'Buy Now' buttons to contact us via Telegram and make your purchase."
}
